djwaiter/__init__.py
djwaiter/admin.py
djwaiter/apps.py
djwaiter/middleware.py
djwaiter/models.py
djwaiter/tests.py
djwaiter/views.py
djwaiter/migrations/__init__.py
django_waiter-0.5.dist-info/LICENSE
django_waiter-0.5.dist-info/METADATA
django_waiter-0.5.dist-info/WHEEL
django_waiter-0.5.dist-info/top_level.txt
django_waiter-0.5.dist-info/RECORD
